README.md
setup.py
triedTree/__init__.py
triedTree/base_tried_tree.py
triedTree/components.py
triedTree/entity_tried_tree.py
triedTree/patten_tried_tree.py
triedTree.egg-info/PKG-INFO
triedTree.egg-info/SOURCES.txt
triedTree.egg-info/dependency_links.txt
triedTree.egg-info/top_level.txt