Metadata-Version: 1.0
Name: triedTree
Version: 0.1.3
Summary: 基于字典树实现实体发现
Home-page: https://github.com/fanfanfeng/triedTree
Author: qiufengfeng
Author-email: 544855237@qq.com
License: LGPL
Platform: UNKNOWN
